[
  {
    "id": "6418580603346044",
    "email": "Monte_Strosin88@yahoo.com"
  },
  {
    "id": "8621305380933033",
    "email": "Abraham_Friesen36@hotmail.com"
  },
  {
    "id": "4910549452296032",
    "email": "Ahmad.Mann32@yahoo.com"
  },
  {
    "id": "4175660547778797",
    "email": "Penelope.McGlynn82@gmail.com"
  },
  {
    "id": "2847120602237011",
    "email": "Elmira.OConnell60@yahoo.com"
  },
  {
    "id": "3334966705504885",
    "email": "Abdullah_Oberbrunner61@hotmail.com"
  },
  {
    "id": "8824835902921178",
    "email": "Antonette.Wyman67@gmail.com"
  },
  {
    "id": "5614910363836866",
    "email": "Fleta_Nitzsche32@yahoo.com"
  },
  {
    "id": "7698853927647856",
    "email": "Loyce.Frami@gmail.com"
  },
  {
    "id": "8092630082061431",
    "email": "Anibal69@yahoo.com"
  },
  {
    "id": "9617148974061018",
    "email": "Price35@yahoo.com"
  },
  {
    "id": "7707272944573371",
    "email": "Sabina94@yahoo.com"
  },
  {
    "id": "3633414668964915",
    "email": "Hayden87@yahoo.com"
  },
  {
    "id": "6592367731462937",
    "email": "Cortez.Turner69@hotmail.com"
  },
  {
    "id": "2517288559576960",
    "email": "Josh14@yahoo.com"
  },
  {
    "id": "3072675071809679",
    "email": "Tyrel.Kozey68@gmail.com"
  },
  {
    "id": "4662014052186234",
    "email": "Dillan98@hotmail.com"
  },
  {
    "id": "9097802208398873",
    "email": "Meredith.Jacobs15@yahoo.com"
  },
  {
    "id": "4524052994794934",
    "email": "Anna.Stark95@yahoo.com"
  },
  {
    "id": "5169828265958283",
    "email": "Gardner19@yahoo.com"
  },
  {
    "id": "1513697119696906",
    "email": "Luther_Gorczany@yahoo.com"
  },
  {
    "id": "7709264969487825",
    "email": "Margarette.Yundt@hotmail.com"
  },
  {
    "id": "1264232518954374",
    "email": "Johathan.Torphy@hotmail.com"
  },
  {
    "id": "8753213152227836",
    "email": "Gwen.Bashirian9@hotmail.com"
  },
  {
    "id": "6295718824127865",
    "email": "Nannie_Larkin78@yahoo.com"
  },
  {
    "id": "8104514877196982",
    "email": "Kobe.Bogisich60@hotmail.com"
  },
  {
    "id": "8450692094564936",
    "email": "Tierra98@gmail.com"
  },
  {
    "id": "5094772002319141",
    "email": "Adelle_Hyatt3@hotmail.com"
  },
  {
    "id": "9916131954270804",
    "email": "Jacklyn64@gmail.com"
  },
  {
    "id": "9877126827823994",
    "email": "Nick_Koch@yahoo.com"
  },
  {
    "id": "8455242596866166",
    "email": "Virginie.Reinger@gmail.com"
  },
  {
    "id": "1501063229426186",
    "email": "Jammie.Wyman64@yahoo.com"
  },
  {
    "id": "8956990866545122",
    "email": "Joaquin17@yahoo.com"
  },
  {
    "id": "4013236253468162",
    "email": "Daija_Bednar@yahoo.com"
  },
  {
    "id": "2634370093348413",
    "email": "Orie.Mayert93@gmail.com"
  },
  {
    "id": "1337716279564804",
    "email": "Ramon.Hoppe@hotmail.com"
  },
  {
    "id": "7649133230010617",
    "email": "Cyrus_Rutherford@yahoo.com"
  },
  {
    "id": "9790592373178645",
    "email": "Laisha10@hotmail.com"
  },
  {
    "id": "9027228098732695",
    "email": "Hulda_Mills7@hotmail.com"
  },
  {
    "id": "7540009203392216",
    "email": "Dante12@gmail.com"
  },
  {
    "id": "4554265859995057",
    "email": "Omer.Klocko28@gmail.com"
  },
  {
    "id": "2895183839181729",
    "email": "Miles.Schmitt86@yahoo.com"
  },
  {
    "id": "2061934795835223",
    "email": "Charles_Barton23@yahoo.com"
  },
  {
    "id": "1160602435867392",
    "email": "Edwina_Ebert11@hotmail.com"
  },
  {
    "id": "7182301320627681",
    "email": "Alfreda82@yahoo.com"
  },
  {
    "id": "8641608258536518",
    "email": "Dayton.Bernier42@gmail.com"
  },
  {
    "id": "7510964541136200",
    "email": "Maryam1@yahoo.com"
  },
  {
    "id": "7672528204528468",
    "email": "Eugenia_Heaney64@hotmail.com"
  },
  {
    "id": "9610501681748349",
    "email": "Kaylah55@yahoo.com"
  },
  {
    "id": "3560050961488259",
    "email": "Clay49@yahoo.com"
  }
]
